assembly_client/__init__.py
assembly_client/api/__init__.py
assembly_client/api/contracts.py
assembly_client/api/job_management.py
assembly_client/api/neo_transactions.py
assembly_client/api/network_client.py
assembly_client/api/network_syncer.py
assembly_client/api/node_api_client.py
assembly_client/api/node_client.py
assembly_client/api/timeout.py
assembly_client/api/types/__init__.py
assembly_client/api/types/date_types.py
assembly_client/api/types/decimal.py
assembly_client/api/types/error_types.py
assembly_client/api/types/event_types.py
assembly_client/api/types/function_type.py
assembly_client/api/types/time_types.py
assembly_client/api/util/__init__.py
assembly_client/api/util/date_time.py
assembly_client/api/util/json.py
assembly_client/api/util/path_util.py
assembly_client/api/util/time.py
test/__init__.py
test/conftest.py
test/test_errors.py
test/test_network_config.py
test/test_publish_contracts.py
symbiont_io.assembly_client-4.1.0.dist-info/LICENSE
symbiont_io.assembly_client-4.1.0.dist-info/METADATA
symbiont_io.assembly_client-4.1.0.dist-info/WHEEL
symbiont_io.assembly_client-4.1.0.dist-info/top_level.txt
symbiont_io.assembly_client-4.1.0.dist-info/RECORD
