Metadata-Version: 2.1
Name: symbiont-io.assembly-client
Version: 4.1.0
Summary: Symbiont Assembly Client
Home-page: http://symbiont.io
Author: Symbiont
Author-email: ecosystem@symbiont.io
Maintainer: Symbiont Ecosystem Team
Maintainer-email: ecosystem@symbiont.io
License: UNKNOWN
Keywords: symbiont
Platform: UNKNOWN
Classifier: Development Status :: 5 - Production/Stable
Classifier: Intended Audience :: Developers
Classifier: Intended Audience :: Financial and Insurance Industry
Classifier: Natural Language :: English
Classifier: Operating System :: POSIX
Classifier: Programming Language :: Python :: 3 :: Only 
Classifier: Topic :: Office/Business :: Financial
Classifier: Topic :: Software Development :: Libraries :: Python Modules
Classifier: Topic :: System :: Distributed Computing
Provides: assembly_client
Requires-Dist: cryptography (==36.0.2)
Requires-Dist: msgpack (==1.0.3)
Requires-Dist: python-dateutil (==2.8.2)
Requires-Dist: pyyaml (==6.0)
Requires-Dist: simplejson (==3.17.6)
Requires-Dist: honeycomb-beeline (==3.0.0)
Requires-Dist: requests (==2.28.0)
